{
  "knife": {
    "timeNeed": 3,
    "require": {
      "iron": 3
    }
  },
  "flyKnife": {
    "timeNeed": 2,
    "require": {
      "knife": 1
    },
    "science": "smith_2"
  },
  "stick": {
    "timeNeed": 2,
    "require": {
      "wood": 4
    },
    "science": "tool"
  },
  "axe": {
    "timeNeed": 3,
    "require": {
      "wood": 4,
      "iron": 4
    }
  },
  "blockAxe": {
    "timeNeed": 5,
    "require": {
      "axe": 1,
      "iron": 40
    },
    "science": "smith_2"
  },
  "hoe": {
    "timeNeed": 3,
    "require": {
      "wood": 4,
      "iron": 4
    },
    "science": "tool"
  },
  "pickaxe": {
    "timeNeed": 3,
    "require": {
      "wood": 4,
      "iron": 4
    },
    "science": "tool"
  },
  "shovel": {
    "timeNeed": 3,
    "require": {
      "wood": 4,
      "iron": 4
    },
    "science": "tool"
  },
  "poizondKnife": {
    "timeNeed": 3,
    "require": {
      "poizon": 4,
      "knife": 1
    },
    "science": "smith_1"
  },
  "shortSword": {
    "timeNeed": 3,
    "require": {
      "wood": 2,
      "iron": 6
    }
  },
  "longSword": {
    "timeNeed": 3,
    "require": {
      "wood": 2,
      "iron": 8
    },
    "science": "smith_1"
  },
  "boneBar": {
    "timeNeed": 3,
    "require": {
      "bone": 20,
      "stick": 1
    },
    "science": "smith_1"
  },
  "spear": {
    "timeNeed": 3,
    "require": {
      "wood": 12,
      "knife": 1
    },
    "science": "smith_1"
  },
  "foolHammer": {
    "timeNeed": 3,
    "require": {
      "part": 20,
      "iron": 20
    },
    "science": "smith_1"
  },
  "milHammer": {
    "timeNeed": 4,
    "require": {
      "mithril": 100
    },
    "science": "smith_2"
  },
  "teethAxe": {
    "timeNeed": 3,
    "require": {
      "wood": 10,
      "teeth": 5
    },
    "science": "smith_2"
  },
  "lightHammer": {
    "timeNeed": 3,
    "require": {
      "part": 100,
      "iron": 100
    },
    "science": "magicWeapon"
  },
  "dragonSword": {
    "timeNeed": 5,
    "require": {
      "dragonBone": 20,
      "mithril": 5
    },
    "event": "dragonQuest"
  },
  "dragonBow": {
    "timeNeed": 5,
    "require": {
      "dragonBone": 40,
      "crystal": 5
    },
    "event": "dragonQuest"
  },
  "bow": {
    "timeNeed": 3,
    "require": {
      "wood": 10,
      "cirrus": 4
    }
  },
  "hornBow": {
    "timeNeed": 3,
    "require": {
      "horn": 4,
      "bow": 1
    },
    "science": "smith_1"
  },
  "poizondBow": {
    "timeNeed": 3,
    "require": {
      "poizon": 4,
      "bow": 1
    },
    "science": "smith_1"
  },
  "poizondHornBow": {
    "timeNeed": 3,
    "require": {
      "horn": 4,
      "poizon": 4,
      "bow": 1
    },
    "science": "smith_1"
  },
  "slingshot": {
    "timeNeed": 3,
    "require": {
      "wood": 4,
      "part": 4,
      "cirrus": 4
    },
    "science": "smith_1"
  },
  "boneSlingshot": {
    "timeNeed": 3,
    "require": {
      "bone": 20,
      "part": 10,
      "slingshot": 1
    },
    "science": "smith_2"
  },
  "handGun": {
    "timeNeed": 3,
    "require": {
      "part": 20,
      "iron": 10
    },
    "science": "smith_1"
  },
  "gun": {
    "timeNeed": 3,
    "require": {
      "part": 30,
      "iron": 25,
      "wood": 10
    },
    "science": "smith_1"
  },
  "sniper": {
    "timeNeed": 3,
    "require": {
      "part": 80,
      "iron": 45,
      "wood": 20
    },
    "science": "smith_2"
  },
  "shotGun": {
    "timeNeed": 5,
    "require": {
      "gun": 1,
      "part": 100
    },
    "science": "gun_expert"
  },
  "goodSniper": {
    "timeNeed": 5,
    "require": {
      "sniper": 1,
      "eagleEye": 4,
      "part": 60
    },
    "science": "gun_expert"
  },
  "jtlGun": {
    "timeNeed": 5,
    "require": {
      "mithril": 100,
      "part": 100,
      "iron": 60
    },
    "science": "gun_expert"
  },
  "iceGun": {
    "timeNeed": 3,
    "require": {
      "gold": 10,
      "part": 80
    },
    "event": "goblin_3"
  },
  "slightArm": {
    "timeNeed": 3,
    "require": {
      "wood": 10,
      "part": 4
    },
    "science": "smith_1"
  },
  "ironArm": {
    "timeNeed": 3,
    "require": {
      "iron": 20,
      "part": 8
    },
    "science": "smith_2"
  },
  "jacket": {
    "timeNeed": 4,
    "require": {
      "silk": 8,
      "fur": 8
    },
    "science": "tailor_1"
  },
  "glove": {
    "timeNeed": 3,
    "require": {
      "silk": 2,
      "fur": 6
    },
    "science": "tailor_1"
  },
  "searchGlove": {
    "timeNeed": 4,
    "require": {
      "silk": 8,
      "fur": 12
    },
    "science": "tailor_2"
  },
  "brassart": {
    "timeNeed": 3,
    "require": {
      "iron": 18,
      "part": 2
    },
    "science": "tailor_2"
  },
  "strGlove": {
    "timeNeed": 3,
    "require": {
      "silk": 6,
      "bark": 4
    },
    "science": "tailor_1"
  },
  "hunterGlove": {
    "timeNeed": 3,
    "require": {
      "silk": 10,
      "eagleEye": 4
    },
    "science": "tailor_2"
  },
  "compass": {
    "timeNeed": 8,
    "require": {
      "gold": 4,
      "part": 8
    },
    "event": "goblin_1"
  },
  "shoe": {
    "timeNeed": 3,
    "require": {
      "fur": 4,
      "silk": 4,
      "rope": 2
    },
    "science": "tailor_1"
  },
  "runShoe": {
    "timeNeed": 3,
    "require": {
      "feather": 4,
      "fur": 3
    },
    "science": "tailor_1"
  },
  "fastShoe": {
    "timeNeed": 3,
    "require": {
      "feather": 4,
      "fur": 3
    },
    "science": "tailor_2"
  },
  "luckyShoe": {
    "timeNeed": 3,
    "require": {
      "silk": 4,
      "fur": 3,
      "gold": 2
    },
    "science": "magicWeapon"
  },
  "advanHat": {
    "timeNeed": 3,
    "require": {
      "feather": 2,
      "silk": 4,
      "rope": 1
    },
    "science": "magicWeapon"
  },
  "probeHat": {
    "timeNeed": 3,
    "require": {
      "eagleEye": 1,
      "iron": 10,
      "part": 20
    },
    "event": "goblin_4"
  },
  "meleeHat": {
    "timeNeed": 3,
    "require": {
      "iron": 10,
      "horn": 2
    },
    "science": "tailor_2"
  },
  "tc130": {
    "timeNeed": 3,
    "require": {
      "gold": 4,
      "part": 10
    },
    "event": "goblin_2"
  },
  "fearlessAxe": {
    "timeNeed": 5,
    "require": {
      "darkGold": 5
    },
    "event": "iceTownEvent_1"
  },
  "fearlessArm": {
    "timeNeed": 3,
    "require": {
      "darkGold": 5
    },
    "event": "iceTownEvent_2"
  },
  "fearlessHat": {
    "timeNeed": 3,
    "require": {
      "darkGold": 5
    },
    "event": "iceTownEvent_3"
  },
  "dungeonRope": {
    "timeNeed": 1,
    "require": {
      "rope": 2
    },
    "science": "dungeonRopeScience"
  },
  "rope": {
    "timeNeed": 1,
    "require": {
      "hay": 5
    },
    "science": "meterial"
  },
  "paper": {
    "timeNeed": 1,
    "require": {
      "bark": 2,
      "water": 1
    },
    "science": "meterial"
  },
  "part": {
    "timeNeed": 1,
    "require": {
      "iron": 2
    },
    "science": "meterial"
  },
  "bumb": {
    "timeNeed": 1,
    "require": {
      "alco": 1,
      "powder": 2,
      "part": 1
    },
    "science": "smith_2"
  },
  "arrow": {
    "timeNeed": 0.1,
    "require": {
      "wood": 1
    }
  },
  "powder": {
    "timeNeed": 0.1,
    "require": {
      "saltpeter": 1
    },
    "science": "smith_1"
  },
  "bullet": {
    "timeNeed": 0.1,
    "require": {
      "powder": 1,
      "iron": 1
    },
    "science": "smith_1"
  }
}
